bibtex2rfc-2.0.0.data/scripts/bibtex2rfc
bibtex2rfc_pkg/__init__.py
bibtex2rfc_pkg/bibxml.py
bibtex2rfc-2.0.0.dist-info/LICENSE
bibtex2rfc-2.0.0.dist-info/METADATA
bibtex2rfc-2.0.0.dist-info/WHEEL
bibtex2rfc-2.0.0.dist-info/top_level.txt
bibtex2rfc-2.0.0.dist-info/RECORD
