Metadata-Version: 2.1
Name: bibtex2rfc
Version: 2.0.0
Summary: Convert BibTeX references to the xml2rfc format
Home-page: https://github.com/yaronf/bibtex2rfc
Author: Yaron Sheffer
Author-email: yaronf.ietf@gmail.com
License: UNKNOWN
Platform: UNKNOWN
Classifier: Programming Language :: Python :: 3
Classifier: License :: Public Domain
Classifier: Operating System :: OS Independent
Requires-Python: >=3.6
Requires-Dist: bibtexparser
